{
  "project_info": {
    "project_number": "503673492651",
    "project_id": "ucscparking-1"
  },
  "client": [
    {
      "client_info": {
        "mobilesdk_app_id": "1:503673492651:android:24ef098d207c7e03",
        "android_client_info": {
          "package_name": "ucsc.cmps121.ucscparking"
        }
      },
      "oauth_client": [
        {
          "client_id": "503673492651-765i6ll64ggmospa1g1jl000tsjgga9h.apps.googleusercontent.com",
          "client_type": 1,
          "android_info": {
            "package_name": "ucsc.cmps121.ucscparking",
            "certificate_hash": "5f12e21a1397df06822f70f2ffccba1b00990a8b"
          }
        },
        {
          "client_id": "503673492651-cidfbq33i6ivfj3ckpp1k1hrvcc6c7ju.apps.googleusercontent.com",
          "client_type": 3
        }
      ],
      "api_key": [
        {
          "current_key": "AIzaSyCfOQWi6tznKMzU_yDKGpLzSfYySojUCD0"
        }
      ],
      "services": {
        "analytics_service": {
          "status": 1
        },
        "appinvite_service": {
          "status": 1,
          "other_platform_oauth_client": []
        },
        "ads_service": {
          "status": 1
        }
      }
    }
  ],
  "configuration_version": "1"
}